AUTHORS
CHANGES.rst
LICENSE
MANIFEST.in
README.rst
setup.py
jsonklog/__init__.py
jsonklog/formatters.py
jsonklog.egg-info/PKG-INFO
jsonklog.egg-info/SOURCES.txt
jsonklog.egg-info/dependency_links.txt
jsonklog.egg-info/entry_points.txt
jsonklog.egg-info/namespace_packages.txt
jsonklog.egg-info/not-zip-safe
jsonklog.egg-info/requires.txt
jsonklog.egg-info/top_level.txt
jsonklog/handlers/__init__.py
jsonklog/handlers/basehandler.py
jsonklog/handlers/elasticsearchhandler.py
jsonklog/handlers/mongodbhandler.py