Metadata-Version: 1.0
Name: jsonklog
Version: 0.15.0
Summary: JSON Logging Library with Python
Home-page: http://www.github.com/neogenix/jsonklog
Author: Patrick Ancillotti
Author-email: patrick@eefy.net
License: Apache 2.0
Keywords: json logging
Platform: UNKNOWN
Classifier: Development Status :: 4 - Beta
Classifier: License :: OSI Approved :: Apache Software License
Classifier: Programming Language :: Python
Classifier: Topic :: Software Development :: Libraries :: Python Modules
Classifier: Topic :: System :: Logging
